poetry_vendoring/__init__.py
poetry_vendoring/plugin.py
poetry_vendoring-0.1.2.dist-info/entry_points.txt
poetry_vendoring-0.1.2.dist-info/WHEEL
poetry_vendoring-0.1.2.dist-info/METADATA
poetry_vendoring-0.1.2.dist-info/RECORD
